check_datapackage/__init__.py
check_datapackage/check.py
check_datapackage/config.py
check_datapackage/constants.py
check_datapackage/examples.py
check_datapackage/exclusion.py
check_datapackage/extensions.py
check_datapackage/internals.py
check_datapackage/issue.py
check_datapackage/py.typed
check_datapackage/read_json.py
check_datapackage/schemas/data-package-2-0.json
check_datapackage-0.30.0.dist-info/METADATA
check_datapackage-0.30.0.dist-info/WHEEL
check_datapackage-0.30.0.dist-info/licenses/LICENSE.md
check_datapackage-0.30.0.dist-info/RECORD
