Metadata-Version: 2.4
Name: check-datapackage
Version: 0.30.0
Summary: Check your Data Package's metadata against the Data Package standard to ensure that it's compliant with the standard
Project-URL: homepage, https://check-datapackage.seedcase-project.org
Project-URL: repository, https://github.com/seedcase-project/check-datapackage
Project-URL: changelog, https://github.com/seedcase-project/check-datapackage/blob/main/CHANGELOG.md
Project-URL: issues, https://github.com/seedcase-project/check-datapackage/issues
Author-email: "Luke W. Johnston" <lwjohnst@gmail.com>, Kristiane Beicher <kris.beicher@clin.au.dk>, Signe Kirk Brødbæk <signekb@clin.au.dk>, Marton Vago <marton.vago95@gmail.com>, Joel Ostblom <joel@joelostblom.com>
Maintainer-email: "Luke W. Johnston" <lwjohnst@gmail.com>, Kristiane Beicher <kris.beicher@clin.au.dk>, Signe Kirk Brødbæk <signekb@clin.au.dk>, Marton Vago <marton.vago95@gmail.com>, Joel Ostblom <joel@joelostblom.com>
License-Expression: MIT
License-File: LICENSE.md
Keywords: checks,data engineering,data package,data package checks,frictionless,frictionless data,metadata,metadata checks,metadata verification,verification
Requires-Python: >=3.12
Requires-Dist: jsonschema>=4.25.1
Requires-Dist: pydantic>=2.12.3
Requires-Dist: python-jsonpath>=2.0.1
Requires-Dist: rich>=14.2.0
Requires-Dist: types-jsonschema>=4.25.1.20250822
